hscp.py
hscp-0.2.0.dist-info/LICENSE
hscp-0.2.0.dist-info/WHEEL
hscp-0.2.0.dist-info/METADATA
hscp-0.2.0.dist-info/RECORD
