Metadata-Version: 2.1
Name: hscp
Version: 0.2.0
Summary: Client library for HyScores.
Home-page: https://github.com/moonburnt/hscp
License: MIT
Author: moonburnt
Author-email: moonburnt@disroot.org
Requires-Python: >=3.9,<4.0
Classifier: License :: OSI Approved :: MIT License
Classifier: Programming Language :: Python :: 3
Classifier: Programming Language :: Python :: 3.10
Classifier: Programming Language :: Python :: 3.9
Requires-Dist: aiohttp (==3.8.1)
Requires-Dist: requests (==2.27.1)
